cheesefactory_excel
