Metadata-Version: 1.1
Name: cheesefactory-excel
Version: 0.4
Summary: Create Excel files from Dataframes or dictionaries.
Home-page: https://bitbucket.org/hellsgrannies/cheesefactory-excel
Author: Todd Salazar
Author-email: unixsal@yahoo.com
License: UNKNOWN
Keywords: cheesefactory excel dataframe pandas development
Platform: UNKNOWN
Classifier: Development Status :: 4 - Beta
Classifier: Intended Audience :: Developers
Classifier: License :: OSI Approved :: BSD License
Classifier: Programming Language :: Python :: 3.7
